asymmetric_matchers/__init__.py
asymmetric_matchers-0.2.0.dist-info/LICENSE
asymmetric_matchers-0.2.0.dist-info/METADATA
asymmetric_matchers-0.2.0.dist-info/WHEEL
asymmetric_matchers-0.2.0.dist-info/top_level.txt
asymmetric_matchers-0.2.0.dist-info/RECORD
