Metadata-Version: 2.1
Name: asymmetric-matchers
Version: 0.2.0
Summary: Asymmetric matchers for testing
Home-page: https://github.com/duailibe/asymmetric-matchers
Author: Lucas Duailibe
Author-email: lucasds@gmail.com
License: Apache-2.0
Project-URL: Documentation, https://github.com/duailibe/asymmetric-matchers
Project-URL: Source Code, https://github.com/duailibe/asymmetric-matchers
Project-URL: Bug Tracker, https://github.com/duailibe/asymmetric-matchers/issues
Keywords: testing asymmetric matchers
Platform: UNKNOWN
Classifier: Development Status :: 3 - Alpha
Classifier: Environment :: Console
Classifier: Intended Audience :: Developers
Classifier: License :: OSI Approved :: Apache Software License
Classifier: Operating System :: OS Independent
Classifier: Programming Language :: Python
Classifier: Programming Language :: Python :: 2
Classifier: Programming Language :: Python :: 2.7
Classifier: Programming Language :: Python :: 3
Classifier: Programming Language :: Python :: 3 :: Only
Classifier: Programming Language :: Python :: 3.7
Classifier: Programming Language :: Python :: 3.8
Classifier: Programming Language :: Python :: 3.9
Classifier: Programming Language :: Python :: 3.10
Classifier: Topic :: Software Development :: Testing
Requires-Python: !=3.0.*,!=3.1.*,!=3.2.*,!=3.3.*,!=3.4.*,!=3.5.*,!=3.6.*,>=2.7
License-File: LICENSE
